yta_file/__init__.py
yta_file/filename/__init__.py
yta_file/filename/dataclasses.py
yta_file/filename/handler.py
yta_file/filename/utils.py
yta_file/handler.py
yta_file/path/__init__.py
yta_file-0.0.15.dist-info/licenses/LICENSE
yta_file-0.0.15.dist-info/METADATA
yta_file-0.0.15.dist-info/WHEEL
yta_file-0.0.15.dist-info/RECORD
